pyEllipse/__init__.py
pyEllipse/confidence_ellipse.py
pyEllipse/hotelling_coordinates.py
pyEllipse/hotelling_parameters.py
pyellipse-0.1.3.dist-info/METADATA
pyellipse-0.1.3.dist-info/WHEEL
pyellipse-0.1.3.dist-info/licenses/LICENSE
pyellipse-0.1.3.dist-info/RECORD
