Metadata-Version: 2.4
Name: pyEllipse
Version: 0.1.3
Summary: Tools for creating and analyzing confidence ellipses, including Hotelling's T-squared ellipses for multivariate statistical analysis and data visualization.
License: MIT
License-File: LICENSE
Keywords: statistics,confidence-ellipse,hotelling,multivariate,visualization
Author: Christian L. Goueguel
Author-email: christian.goueguel@gmail.com
Requires-Python: >=3.9,<3.14
Classifier: Development Status :: 5 - Production/Stable
Classifier: Intended Audience :: Science/Research
Classifier: License :: OSI Approved :: MIT License
Classifier: Programming Language :: Python :: 3
Classifier: Programming Language :: Python :: 3.9
Classifier: Programming Language :: Python :: 3.10
Classifier: Programming Language :: Python :: 3.11
Classifier: Programming Language :: Python :: 3.12
Classifier: Programming Language :: Python :: 3.13
Classifier: Programming Language :: Python :: 3.8
Classifier: Topic :: Scientific/Engineering :: Mathematics
Classifier: Topic :: Scientific/Engineering :: Visualization
Provides-Extra: all
Provides-Extra: plotting
Requires-Dist: matplotlib (>=3.7.0,<4.0.0)
Requires-Dist: numpy (>=1.24.0,<2.0.0)
Requires-Dist: pandas (>=2.0.0,<3.0.0)
Requires-Dist: plotly (>=5.14.0,<6.0.0) ; extra == "plotting" or extra == "all"
Requires-Dist: scikit-learn (>=1.3.0,<2.0.0)
Requires-Dist: scipy (>=1.11.0,<2.0.0)
Requires-Dist: seaborn (>=0.12.0,<0.13.0) ; extra == "plotting" or extra == "all"
Project-URL: Bug Tracker, https://github.com/ChristianGoueguel/pyEllipse/issues
Project-URL: Documentation, https://christiangoueguel.github.io/pyEllipse
Project-URL: Homepage, https://github.com/ChristianGoueguel/pyEllipse
Project-URL: Repository, https://github.com/ChristianGoueguel/pyEllipse
